LICENSE
README.md
setup.py
lequangdung.egg-info/PKG-INFO
lequangdung.egg-info/SOURCES.txt
lequangdung.egg-info/dependency_links.txt
lequangdung.egg-info/requires.txt
lequangdung.egg-info/top_level.txt
mail10plequangdung/__init__.py
mail10plequangdung/mail.py