Metadata-Version: 2.1
Name: lequangdung
Version: 0.0.2
Summary: Lê Quang Dũng 2007
Home-page: UNKNOWN
Author: Le Quang Dung
Author-email: <dunggdepptryy@gmail.com>
License: UNKNOWN
Keywords: lequangdung,lequangdung2007,lequangdung17092007,mail10plequangdung
Platform: UNKNOWN
Classifier: Development Status :: 1 - Planning
Classifier: Intended Audience :: Developers
Classifier: Programming Language :: Python :: 3
Classifier: Operating System :: Unix
Classifier: Operating System :: MacOS :: MacOS X
Classifier: Operating System :: Microsoft :: Windows
License-File: LICENSE
